pyrfdata/__init__.py
pyrfdata/cell_generator.py
pyrfdata/file.py
pyrfdata/partition.py
pyrfdata/request.py
pyrfdata/run.py
pyrfdata/template.py
pyrfdata/util.py
pyrfdata-0.0.3.dist-info/LICENSE
pyrfdata-0.0.3.dist-info/METADATA
pyrfdata-0.0.3.dist-info/NOTICE
pyrfdata-0.0.3.dist-info/WHEEL
pyrfdata-0.0.3.dist-info/entry_points.txt
pyrfdata-0.0.3.dist-info/top_level.txt
pyrfdata-0.0.3.dist-info/RECORD
