Metadata-Version: 2.1
Name: pyrfdata
Version: 0.0.3
Summary: pyrfdata generates data for performance testing
Home-page: https://github.com/prasanna/pyrfdata
Author: Prasanna Pendse
Author-email: prasanna.pendse@gmail.com
License: UNKNOWN
Platform: UNKNOWN
Classifier: Programming Language :: Python :: 3
Classifier: License :: OSI Approved :: Apache Software License
Classifier: Operating System :: OS Independent
Requires-Python: >=3.6
Requires-Dist: pyyaml
